<?xml version="1.0" ?>
<!DOCTYPE PubmedArticleSet PUBLIC "-//NLM//DTD PubMedArticle, 1st January 2025//EN" "https://dtd.nlm.nih.gov/ncbi/pubmed/out/pubmed_250101.dtd">
<PubmedArticleSet>
<PubmedArticle><MedlineCitation Status="MEDLINE" Owner="NLM" IndexingMethod="Automated"><PMID Version="1">40441496</PMID><DateCompleted><Year>2025</Year><Month>09</Month><Day>21</Day></DateCompleted><DateRevised><Year>2025</Year><Month>09</Month><Day>21</Day></DateRevised><Article PubModel="Print-Electronic"><Journal><ISSN IssnType="Electronic">1528-0012</ISSN><JournalIssue CitedMedium="Internet"><Volume>169</Volume><Issue>5</Issue><PubDate><Year>2025</Year><Month>Oct</Month></PubDate></JournalIssue><Title>Gastroenterology</Title><ISOAbbreviation>Gastroenterology</ISOAbbreviation></Journal><ArticleTitle>Efficacy of ACupuncTure in Irritable bOwel syNdrome (ACTION): A Multicenter Randomized Controlled Trial.</ArticleTitle><Pagination><StartPage>958</StartPage><EndPage>969.e5</EndPage><MedlinePgn>958-969.e5</MedlinePgn></Pagination><ELocationID EIdType="doi" ValidYN="Y">10.1053/j.gastro.2025.05.016</ELocationID><ELocationID EIdType="pii" ValidYN="Y">S0016-5085(25)00826-1</ELocationID><Abstract><AbstractText Label="BACKGROUND &amp; AIMS" NlmCategory="OBJECTIVE">Irritable bowel syndrome (IBS) affects 4.1% of the adult population, with many reporting ongoing symptoms despite first-line therapies. Acupuncture is widely used for IBS, but without sufficient evidence. We aimed to assess the efficacy of acupuncture in patients with diarrhea-predominant IBS (IBS-D).</AbstractText><AbstractText Label="METHODS" NlmCategory="METHODS">This was a multicenter randomized controlled trial in 6 hospitals in China. Patients aged 18 to 75 years with IBS-D per Rome IV diagnostic criteria were randomly allocated (1:1) to receive 15 sessions of acupuncture or sham acupuncture (blunt-tipped needle at non-acupoints) over 6 weeks with a 12-week follow-up. The primary outcome was the composite response rate at week 6, defined as at least a 30% improvement in the mean worst abdominal pain and a 50% or more reduction in the number of days with diarrhea from baseline during week 6.</AbstractText><AbstractText Label="RESULTS" NlmCategory="RESULTS">Between May 2021 and August 2022, 584 patients were assessed for eligibility, of whom 280 were randomly allocated. The primary outcome was reached by 71 (57.9%) patients in the acupuncture group compared with 47 (41.4%) patients in the sham acupuncture group (risk ratio 1.40; P = .008). The between-group difference became significant from week 3 and maintained throughout the study except week 16. No severe adverse event was reported.</AbstractText><AbstractText Label="CONCLUSIONS" NlmCategory="CONCLUSIONS">Acupuncture improved abdominal pain and stool consistency in patients with IBS-D, with sustained efficacy over 18 weeks. The results of this trial suggest that acupuncture may serve as an alternative treatment for IBS-D. (ACTION Chinese Clinical Trial Registry number, ChiCTR2100044762).</AbstractText><CopyrightInformation>Copyright &#xa9; 2025 AGA Institute. Published by Elsevier Inc. All rights reserved.</CopyrightInformation></Abstract><AuthorList CompleteYN="Y"><Author ValidYN="Y"><LastName>Yang</LastName><ForeName>Jing-Wen</ForeName><Initials>JW</Initials><AffiliationInfo><Affiliation>International Acupuncture and Moxibustion Innovation Institute, School of Acupuncture-Moxibustion and Tuina, Beijing University of Chinese Medicine, Beijing, China.</Affiliation></AffiliationInfo></Author><Author ValidYN="Y"><LastName>Qi</LastName><ForeName>Ling-Yu</ForeName><Initials>LY</Initials><AffiliationInfo><Affiliation>International Acupuncture and Moxibustion Innovation Institute, School of Acupuncture-Moxibustion and Tuina, Beijing University of Chinese Medicine, Beijing, China.</Affiliation></AffiliationInfo></Author><Author ValidYN="Y"><LastName>Yan</LastName><ForeName>Shi-Yan</ForeName><Initials>SY</Initials><AffiliationInfo><Affiliation>International Acupuncture and Moxibustion Innovation Institute, School of Acupuncture-Moxibustion and Tuina, Beijing University of Chinese Medicine, Beijing, China.</Affiliation></AffiliationInfo></Author><Author ValidYN="Y"><LastName>She</LastName><ForeName>Yan-Fen</ForeName><Initials>YF</Initials><AffiliationInfo><Affiliation>School of Acupuncture-Moxibustion and Tuina, Hebei University of Traditional Chinese Medicine, Shijiazhuang, China.</Affiliation></AffiliationInfo></Author><Author ValidYN="Y"><LastName>Li</LastName><ForeName>Ying</ForeName><Initials>Y</Initials><AffiliationInfo><Affiliation>Acupuncture and Tuina School, Chengdu University of Traditional Chinese Medicine, Chengdu, China.</Affiliation></AffiliationInfo></Author><Author ValidYN="Y"><LastName>Chi</LastName><ForeName>Li-Li</ForeName><Initials>LL</Initials><AffiliationInfo><Affiliation>Department of Spleen and Stomach Diseases, Affiliated Hospital of Shandong University of Traditional Chinese Medicine, Jinan, China.</Affiliation></AffiliationInfo></Author><Author ValidYN="Y"><LastName>Hu</LastName><ForeName>Hui</ForeName><Initials>H</Initials><AffiliationInfo><Affiliation>Department of Acupuncture and Moxibustion, Dongfang Hospital, Beijing University of Chinese Medicine, Beijing, China.</Affiliation></AffiliationInfo></Author><Author ValidYN="Y"><LastName>Wang</LastName><ForeName>Li-Qiong</ForeName><Initials>LQ</Initials><AffiliationInfo><Affiliation>International Acupuncture and Moxibustion Innovation Institute, School of Acupuncture-Moxibustion and Tuina, Beijing University of Chinese Medicine, Beijing, China.</Affiliation></AffiliationInfo></Author><Author ValidYN="Y"><LastName>Ji</LastName><ForeName>Chang-Chun</ForeName><Initials>CC</Initials><AffiliationInfo><Affiliation>Department of Acupuncture and Moxibustion, Shaanxi Hospital of Traditional Chinese Medicine, Xi'an, China.</Affiliation></AffiliationInfo></Author><Author ValidYN="Y"><LastName>Wu</LastName><ForeName>Bang-Qi</ForeName><Initials>BQ</Initials><AffiliationInfo><Affiliation>National Acupuncture and Moxibustion Clinical Medical Research Center, the First Teaching Hospital of Tianjin University of Traditional Chinese Medicine, Tianjin, China.</Affiliation></AffiliationInfo></Author><Author ValidYN="Y"><LastName>Fu</LastName><ForeName>Zi-Tong</ForeName><Initials>ZT</Initials><AffiliationInfo><Affiliation>International Acupuncture and Moxibustion Innovation Institute, School of Acupuncture-Moxibustion and Tuina, Beijing University of Chinese Medicine, Beijing, China.</Affiliation></AffiliationInfo></Author><Author ValidYN="Y"><LastName>Li</LastName><ForeName>Shuang-Jing</ForeName><Initials>SJ</Initials><AffiliationInfo><Affiliation>International Acupuncture and Moxibustion Innovation Institute, School of Acupuncture-Moxibustion and Tuina, Beijing University of Chinese Medicine, Beijing, China.</Affiliation></AffiliationInfo></Author><Author ValidYN="Y"><LastName>Yang</LastName><ForeName>Na-Na</ForeName><Initials>NN</Initials><AffiliationInfo><Affiliation>International Acupuncture and Moxibustion Innovation Institute, School of Acupuncture-Moxibustion and Tuina, Beijing University of Chinese Medicine, Beijing, China.</Affiliation></AffiliationInfo></Author><Author ValidYN="Y"><LastName>Wang</LastName><ForeName>Yu</ForeName><Initials>Y</Initials><AffiliationInfo><Affiliation>International Acupuncture and Moxibustion Innovation Institute, School of Acupuncture-Moxibustion and Tuina, Beijing University of Chinese Medicine, Beijing, China.</Affiliation></AffiliationInfo></Author><Author ValidYN="Y"><LastName>Liu</LastName><ForeName>Cun-Zhi</ForeName><Initials>CZ</Initials><AffiliationInfo><Affiliation>International Acupuncture and Moxibustion Innovation Institute, School of Acupuncture-Moxibustion and Tuina, Beijing University of Chinese Medicine, Beijing, China. Electronic address: lcz623780@126.com.</Affiliation></AffiliationInfo></Author></AuthorList><Language>eng</Language><PublicationTypeList><PublicationType UI="D016428">Journal Article</PublicationType><PublicationType UI="D016448">Multicenter Study</PublicationType><PublicationType UI="D016449">Randomized Controlled Trial</PublicationType></PublicationTypeList><ArticleDate DateType="Electronic"><Year>2025</Year><Month>05</Month><Day>27</Day></ArticleDate></Article><MedlineJournalInfo><Country>United States</Country><MedlineTA>Gastroenterology</MedlineTA><NlmUniqueID>0374630</NlmUniqueID><ISSNLinking>0016-5085</ISSNLinking></MedlineJournalInfo><CitationSubset>IM</CitationSubset><MeshHeadingList><MeshHeading><DescriptorName UI="D006801" MajorTopicYN="N">Humans</DescriptorName></MeshHeading><MeshHeading><DescriptorName UI="D043183" MajorTopicYN="Y">Irritable Bowel Syndrome</DescriptorName><QualifierName UI="Q000628" MajorTopicYN="N">therapy</QualifierName><QualifierName UI="Q000150" MajorTopicYN="N">complications</QualifierName><QualifierName UI="Q000175" MajorTopicYN="N">diagnosis</QualifierName></MeshHeading><MeshHeading><DescriptorName UI="D008297" MajorTopicYN="N">Male</DescriptorName></MeshHeading><MeshHeading><DescriptorName UI="D005260" MajorTopicYN="N">Female</DescriptorName></MeshHeading><MeshHeading><DescriptorName UI="D015670" MajorTopicYN="Y">Acupuncture Therapy</DescriptorName><QualifierName UI="Q000379" MajorTopicYN="N">methods</QualifierName><QualifierName UI="Q000009" MajorTopicYN="N">adverse effects</QualifierName></MeshHeading><MeshHeading><DescriptorName UI="D000328" MajorTopicYN="N">Adult</DescriptorName></MeshHeading><MeshHeading><DescriptorName UI="D008875" MajorTopicYN="N">Middle Aged</DescriptorName></MeshHeading><MeshHeading><DescriptorName UI="D016896" MajorTopicYN="N">Treatment Outcome</DescriptorName></MeshHeading><MeshHeading><DescriptorName UI="D015746" MajorTopicYN="Y">Abdominal Pain</DescriptorName><QualifierName UI="Q000209" MajorTopicYN="N">etiology</QualifierName><QualifierName UI="Q000628" MajorTopicYN="N">therapy</QualifierName></MeshHeading><MeshHeading><DescriptorName UI="D003967" MajorTopicYN="Y">Diarrhea</DescriptorName><QualifierName UI="Q000628" MajorTopicYN="N">therapy</QualifierName><QualifierName UI="Q000209" MajorTopicYN="N">etiology</QualifierName></MeshHeading><MeshHeading><DescriptorName UI="D055815" MajorTopicYN="N">Young Adult</DescriptorName></MeshHeading><MeshHeading><DescriptorName UI="D000368" MajorTopicYN="N">Aged</DescriptorName></MeshHeading><MeshHeading><DescriptorName UI="D002681" MajorTopicYN="N" Type="Geographic">China</DescriptorName></MeshHeading><MeshHeading><DescriptorName UI="D000293" MajorTopicYN="N">Adolescent</DescriptorName></MeshHeading></MeshHeadingList><KeywordList Owner="NOTNLM"><Keyword MajorTopicYN="N">Abdominal Pain</Keyword><Keyword MajorTopicYN="N">Acupuncture</Keyword><Keyword MajorTopicYN="N">Clinical Trial</Keyword><Keyword MajorTopicYN="N">Diarrhea</Keyword><Keyword MajorTopicYN="N">Irritable Bowel Syndrome</Keyword></KeywordList></MedlineCitation><PubmedData><History><PubMedPubDate PubStatus="received"><Year>2024</Year><Month>8</Month><Day>30</Day></PubMedPubDate><PubMedPubDate PubStatus="revised"><Year>2025</Year><Month>4</Month><Day>28</Day></PubMedPubDate><PubMedPubDate PubStatus="accepted"><Year>2025</Year><Month>5</Month><Day>1</Day></PubMedPubDate><PubMedPubDate PubStatus="pubmed"><Year>2025</Year><Month>5</Month><Day>30</Day><Hour>2</Hour><Minute>7</Minute></PubMedPubDate><PubMedPubDate PubStatus="medline"><Year>2025</Year><Month>9</Month><Day>22</Day><Hour>0</Hour><Minute>29</Minute></PubMedPubDate><PubMedPubDate PubStatus="entrez"><Year>2025</Year><Month>5</Month><Day>29</Day><Hour>19</Hour><Minute>35</Minute></PubMedPubDate></History><PublicationStatus>ppublish</PublicationStatus><ArticleIdList><ArticleId IdType="pubmed">40441496</ArticleId><ArticleId IdType="doi">10.1053/j.gastro.2025.05.016</ArticleId><ArticleId IdType="pii">S0016-5085(25)00826-1</ArticleId></ArticleIdList></PubmedData></PubmedArticle></PubmedArticleSet>